LingjiedeXunxi/Dockerfile
LingjiedeXunxi/README.md
LingjiedeXunxi/__init__.py
LingjiedeXunxi/__main__.py
LingjiedeXunxi/file.epub
LingjiedeXunxi/index.html
LingjiedeXunxi/css/__init__.py
LingjiedeXunxi/css/annotations.css
LingjiedeXunxi/css/main.css
LingjiedeXunxi/css/normalize.css
LingjiedeXunxi/css/popup.css
LingjiedeXunxi/font/__init__.py
LingjiedeXunxi/font/fontello.eot
LingjiedeXunxi/font/fontello.svg
LingjiedeXunxi/font/fontello.ttf
LingjiedeXunxi/font/fontello.woff
LingjiedeXunxi/img/__init__.py
LingjiedeXunxi/img/annotator-glyph-sprite.png
LingjiedeXunxi/img/annotator-icon-sprite.png
LingjiedeXunxi/img/apple-touch-icon.png
LingjiedeXunxi/img/cancelfullscreen.png
LingjiedeXunxi/img/close.png
LingjiedeXunxi/img/fullscreen.png
LingjiedeXunxi/img/loader.gif
LingjiedeXunxi/img/menu-icon.png
LingjiedeXunxi/img/save.png
LingjiedeXunxi/img/saved.png
LingjiedeXunxi/img/settings-s.png
LingjiedeXunxi/img/settings.png
LingjiedeXunxi/img/star.png
LingjiedeXunxi/js/__init__.py
LingjiedeXunxi/js/epub.js
LingjiedeXunxi/js/epub.min.js
LingjiedeXunxi/js/epub.min.map
LingjiedeXunxi/js/hooks.min.js
LingjiedeXunxi/js/hooks.min.map
LingjiedeXunxi/js/reader.js
LingjiedeXunxi/js/reader.js.map
LingjiedeXunxi/js/reader.min.js
LingjiedeXunxi/js/reader.min.map
LingjiedeXunxi/js/hooks/__init__.py
LingjiedeXunxi/js/hooks/extensions/__init__.py
LingjiedeXunxi/js/hooks/extensions/highlight.js
LingjiedeXunxi/js/libs/__init__.py
LingjiedeXunxi/js/libs/jquery.min.js
LingjiedeXunxi/js/libs/localforage.min.js
LingjiedeXunxi/js/libs/screenfull.js
LingjiedeXunxi/js/libs/screenfull.min.js
LingjiedeXunxi/js/libs/zip.min.js
LingjiedeXunxi/js/plugins/__init__.py
LingjiedeXunxi/js/plugins/hypothesis.js
LingjiedeXunxi/js/plugins/search.js
lingjiede_xunxi-2022.10.9.1.dist-info/METADATA
lingjiede_xunxi-2022.10.9.1.dist-info/WHEEL
lingjiede_xunxi-2022.10.9.1.dist-info/entry_points.txt
lingjiede_xunxi-2022.10.9.1.dist-info/top_level.txt
lingjiede_xunxi-2022.10.9.1.dist-info/RECORD
